nerfboost.cp311-win_amd64.pyd
nerfboost-1.0.1.dist-info/LICENCE.txt
nerfboost-1.0.1.dist-info/METADATA
nerfboost-1.0.1.dist-info/WHEEL
nerfboost-1.0.1.dist-info/top_level.txt
nerfboost-1.0.1.dist-info/RECORD
