Metadata-Version: 2.1
Name: nerfboost
Version: 1.0.1
Summary: A CUDA-enhanced package for common NeRF model operations
Author: Akshay Pappu
License: MIT License (MIT)
Requires-Python: >=3.8
License-File: LICENCE.txt
Requires-Dist: torch
